comfy_pack-0.4.4.dist-info/METADATA
comfy_pack-0.4.4.dist-info/WHEEL
comfy_pack-0.4.4.dist-info/entry_points.txt
comfy_pack-0.4.4.dist-info/licenses/LICENSE
comfy_pack/__init__.py
comfy_pack/cli.py
comfy_pack/const.py
comfy_pack/hash.py
comfy_pack/model_helper.py
comfy_pack/package.py
comfy_pack/run.py
comfy_pack/service.py
comfy_pack/setup_workspace.sh
comfy_pack/utils.py
comfy_pack-0.4.4.dist-info/RECORD
