Metadata-Version: 2.1
Name: comfy-pack
Version: 0.4.4
Summary: A comprehensive toolkit for standardizing, packaging and deploying ComfyUI workflows as reproducible environments and production-ready REST services
Author-Email: Frost Ming <frost@bentoml.com>
Classifier: Programming Language :: Python :: 3
Classifier: License :: OSI Approved :: Apache Software License
Classifier: Operating System :: OS Independent
Project-URL: Homepage, https://github.com/bentoml/comfy-pack
Requires-Python: >=3.9
Requires-Dist: bentoml>=1.3.21
Requires-Dist: click>=8.1.7
Requires-Dist: comfy-cli>=1.2.8
